lowercase_booleans/__init__.py
lowercase_booleans-1.0.0.dist-info/AUTHORS
lowercase_booleans-1.0.0.dist-info/LICENSE
lowercase_booleans-1.0.0.dist-info/METADATA
lowercase_booleans-1.0.0.dist-info/WHEEL
lowercase_booleans-1.0.0.dist-info/top_level.txt
lowercase_booleans-1.0.0.dist-info/RECORD
