Metadata-Version: 2.1
Name: lowercase-booleans
Version: 1.0.0
Summary: lowercase booleans for python
Home-page: https://github.com/jonathanhacker/lowercase_booleans
Author: Jonathan Hacker
Author-email: github@jhacker.de
License: UNKNOWN
Platform: UNKNOWN
Classifier: Programming Language :: Python :: 3
Classifier: License :: OSI Approved :: MIT License
Classifier: Operating System :: OS Independent
